bindings_help/__init__.py
bindings_help/cli.py
bindings_help/parser.py
confhelp-0.5.0.dist-info/METADATA
confhelp-0.5.0.dist-info/WHEEL
confhelp-0.5.0.dist-info/entry_points.txt
confhelp-0.5.0.dist-info/licenses/LICENSE
confhelp-0.5.0.dist-info/RECORD
