Metadata-Version: 2.4
Name: confhelp
Version: 0.5.0
Summary: Config-driven parser for keybindings with fzf interface
Author: Piotr Zaniewski
License-Expression: MIT
License-File: LICENSE
Classifier: License :: OSI Approved :: MIT License
Classifier: Operating System :: OS Independent
Classifier: Programming Language :: Python :: 3
Classifier: Programming Language :: Python :: 3.9
Classifier: Programming Language :: Python :: 3.10
Classifier: Programming Language :: Python :: 3.11
Classifier: Programming Language :: Python :: 3.12
Requires-Python: >=3.9
Requires-Dist: iterfzf>=1.0
Requires-Dist: tomli>=2.0; python_version < '3.11'
Provides-Extra: dev
Requires-Dist: pytest>=8.0; extra == 'dev'
Requires-Dist: ruff>=0.1; extra == 'dev'
